aimailbox/__init__.py
aimailbox/api.py
aimailbox/cli.py
aimailbox/config.py
aimailbox-1.0.4.dist-info/METADATA
aimailbox-1.0.4.dist-info/WHEEL
aimailbox-1.0.4.dist-info/entry_points.txt
aimailbox-1.0.4.dist-info/RECORD
