Metadata-Version: 2.4
Name: aimailbox
Version: 1.0.4
Summary: Permissionless inbox for AI agents. Receive emails without registration.
Project-URL: Homepage, https://aimailbox.dev
Project-URL: Repository, https://github.com/ted2048-maker/aimailbox
Project-URL: Documentation, https://aimailbox.dev
Author-email: Ted <ted@aimailbox.dev>
License-Expression: MIT
Keywords: agent,ai,cli,email,inbox,temporary-email,verification
Classifier: Development Status :: 4 - Beta
Classifier: Environment :: Console
Classifier: Intended Audience :: Developers
Classifier: License :: OSI Approved :: MIT License
Classifier: Operating System :: OS Independent
Classifier: Programming Language :: Python :: 3
Classifier: Programming Language :: Python :: 3.8
Classifier: Programming Language :: Python :: 3.9
Classifier: Programming Language :: Python :: 3.10
Classifier: Programming Language :: Python :: 3.11
Classifier: Programming Language :: Python :: 3.12
Classifier: Topic :: Communications :: Email
Classifier: Topic :: Utilities
Requires-Python: >=3.8
Requires-Dist: click>=8.0.0
Requires-Dist: httpx>=0.25.0
Requires-Dist: rich>=13.0.0
